fabiplus/__init__.py
fabiplus/admin/__init__.py
fabiplus/admin/logs.py
fabiplus/admin/routes.py
fabiplus/admin/static/css/admin.css
fabiplus/admin/static/css/bootstrap-icons@1.10.0.css
fabiplus/admin/static/css/bootstrap@5.3.css
fabiplus/admin/static/js/admin.js
fabiplus/admin/static/js/bootstrap.bundle.min.js
fabiplus/admin/static/js/unpkg.js
fabiplus/admin/templates/activities.html
fabiplus/admin/templates/analytics.html
fabiplus/admin/templates/auth/login.html
fabiplus/admin/templates/base.html
fabiplus/admin/templates/dashboard.html
fabiplus/admin/templates/logs.html
fabiplus/admin/templates/model_form.html
fabiplus/admin/templates/model_list.html
fabiplus/admin/templates/security.html
fabiplus/admin/templates/settings.html
fabiplus/admin/ui.py
fabiplus/api/__init__.py
fabiplus/api/auto.py
fabiplus/cli/__init__.py
fabiplus/cli/commands/__init__.py
fabiplus/cli/commands/app.py
fabiplus/cli/commands/cache.py
fabiplus/cli/commands/database.py
fabiplus/cli/commands/dev.py
fabiplus/cli/commands/project.py
fabiplus/cli/commands/server.py
fabiplus/cli/commands/user.py
fabiplus/cli/main.py
fabiplus/cli/templates/__init__.py
fabiplus/cli/templates/app.py
fabiplus/cli/templates/project.py
fabiplus/conf/__init__.py
fabiplus/conf/settings.py
fabiplus/core/__init__.py
fabiplus/core/activity.py
fabiplus/core/app.py
fabiplus/core/apps.py
fabiplus/core/auth.py
fabiplus/core/cache.py
fabiplus/core/custom_auth.py
fabiplus/core/docs.py
fabiplus/core/media/__init__.py
fabiplus/core/media/handlers.py
fabiplus/core/media/middleware.py
fabiplus/core/media/models.py
fabiplus/core/media/processors.py
fabiplus/core/media/routes.py
fabiplus/core/media/storage.py
fabiplus/core/media/validators.py
fabiplus/core/migrations.py
fabiplus/core/models.py
fabiplus/core/orm/__init__.py
fabiplus/core/orm/base.py
fabiplus/core/orm/sqlalchemy.py
fabiplus/core/orm/sqlmodel.py
fabiplus/core/orm/tortoise.py
fabiplus/core/permissions/__init__.py
fabiplus/core/permissions/base.py
fabiplus-1.0.0.dist-info/LICENSE
fabiplus-1.0.0.dist-info/METADATA
fabiplus-1.0.0.dist-info/WHEEL
fabiplus-1.0.0.dist-info/entry_points.txt
fabiplus-1.0.0.dist-info/RECORD
