Metadata-Version: 2.3
Name: fabiplus
Version: 1.0.0
Summary: FABI+ Framework - Production-ready, modular, extensible API-only Python framework
License: MIT
Keywords: fabiplus,fabiplus-framework,fastapi,django,framework,api,web,backend,python,cli,admin,orm,django-like,sqlmodel,sqlalchemy,helevon,helevon-technologies-ltd,helevon-framework,fabiplus-framework-helevon-technologies-ltd
Author: FABI+ Development Team
Author-email: team@fabiplus.dev
Requires-Python: >=3.10,<4.0
Classifier: Development Status :: 4 - Beta
Classifier: Environment :: Web Environment
Classifier: Framework :: FastAPI
Classifier: Intended Audience :: Developers
Classifier: License :: OSI Approved :: MIT License
Classifier: Operating System :: OS Independent
Classifier: Programming Language :: Python :: 3
Classifier: Programming Language :: Python :: 3.10
Classifier: Programming Language :: Python :: 3.11
Classifier: Programming Language :: Python :: 3.12
Classifier: Programming Language :: Python :: 3.13
Classifier: Topic :: Internet :: WWW/HTTP :: Dynamic Content
Classifier: Topic :: Internet :: WWW/HTTP :: HTTP Servers
Classifier: Topic :: Software Development :: Libraries :: Application Frameworks
Classifier: Topic :: Software Development :: Libraries :: Python Modules
Provides-Extra: monitoring
Provides-Extra: mysql
Provides-Extra: postgresql
Provides-Extra: redis
Provides-Extra: tortoise
Requires-Dist: aerich (>=0.7.0) ; extra == "tortoise"
Requires-Dist: aiofiles (>=23.2.1)
Requires-Dist: alembic (>=1.13.0)
Requires-Dist: bcrypt (>=4.1.0)
Requires-Dist: fastapi (>=0.104.0)
Requires-Dist: hiredis (>=2.2.0) ; extra == "redis"
Requires-Dist: jinja2 (>=3.1.2)
Requires-Dist: orjson (>=3.9.0)
Requires-Dist: passlib[bcrypt] (>=1.7.4)
Requires-Dist: pillow (>=10.0.0)
Requires-Dist: psycopg2-binary (>=2.9.0) ; extra == "postgresql"
Requires-Dist: pydantic-settings (>=2.1.0)
Requires-Dist: pydantic[email] (>=2.5.0)
Requires-Dist: pymysql (>=1.1.0) ; extra == "mysql"
Requires-Dist: pypdf (>=4.0.0)
Requires-Dist: python-dotenv (>=1.0.0)
Requires-Dist: python-jose[cryptography] (>=3.3.0)
Requires-Dist: python-magic (>=0.4.27)
Requires-Dist: python-multipart (>=0.0.6)
Requires-Dist: redis (>=5.0.0) ; extra == "redis"
Requires-Dist: rich (>=13.0.0)
Requires-Dist: sentry-sdk (>=1.38.0) ; extra == "monitoring"
Requires-Dist: sqlalchemy (>=2.0.0)
Requires-Dist: sqlmodel (>=0.0.14)
Requires-Dist: tortoise-orm (>=0.20.0) ; extra == "tortoise"
Requires-Dist: typer (>=0.9.0,<0.12.0)
Requires-Dist: uvicorn[standard] (>=0.24.0)
Project-URL: Documentation, https://fabiplus.helevon.org
Project-URL: Homepage, https://github.com/Helevon-Technologies-LTD/fabiplus
Project-URL: Repository, https://github.com/Helevon-Technologies-LTD/fabiplus
